{
  "approx_date": "2023-07",
  "yt_title": null,
  "business_ideas": [
    {
      "idea": "Create Costco/Walmart-exclusive versions of premium products like Oura Ring, Eight Sleep at lower price",
      "who": "Shaan",
      "conviction": "serious"
    },
    {
      "idea": "Tech All-Star hackathon weekend: CEOs recruit teams to build, pitch products on stage live",
      "who": "Shaan",
      "conviction": "serious"
    }
  ],
  "predictions": [
    {
      "who": "Shaan",
      "text": "D2C creator platforms will have 'Shopify moment' enabling independent monetization without marketplace discovery"
    },
    {
      "who": "Shaan",
      "text": "Tech executives will engage in friendly competitive events similar to sports leagues"
    }
  ]
}
