{
  "approx_date": "2024-10",
  "yt_title": null,
  "business_ideas": [
    {
      "idea": "What if I did something this way",
      "who": "Panel",
      "conviction": "serious"
    }
  ],
  "predictions": [
    {
      "who": "Panel",
      "text": "will be destroyed by me making such a drastic change in"
    },
    {
      "who": "Panel",
      "text": "will ever spend many times over, but they still do thin"
    },
    {
      "who": "Panel",
      "text": "will sort of speak uh where they're devotin"
    },
    {
      "who": "Panel",
      "text": "will invest specifically in people they know are kin"
    },
    {
      "who": "Panel",
      "text": "will momentarily, but the get trick of the game is, \"Hey, you don't have to wait for the thin"
    }
  ]
}