{
  "approx_date": "2025-02",
  "yt_title": null,
  "business_ideas": [
    {
      "idea": "Zuru Tick: automated factory for building customized houses at $500/sq meter using Dreamcatcher AI design software and robot production",
      "who": "Nick",
      "conviction": "already building/built"
    }
  ],
  "predictions": [
    {
      "who": "Nick",
      "text": "Each of 5 FMCG vertical categories (diapers, beauty, pet food, home care, supplements) will individually be bigger than toy company within 2-3 years"
    },
    {
      "who": "Nick",
      "text": "Zuru Tick housing automation will be transformational in how the world builds; 5 test houses away from perfect product"
    }
  ]
}
