{
  "approx_date": "2025-05",
  "yt_title": null,
  "business_ideas": [
    {
      "idea": "High-agency as a meme and personal development framework (highagency.com)",
      "who": "George",
      "conviction": "already building/built"
    },
    {
      "idea": "Negative visualization meditation app: daily immersive hardship scenarios for gratitude",
      "who": "George",
      "conviction": "serious"
    },
    {
      "idea": "Cure people of cultural bias (anti-Duolingo): teach global perspective vs nationalism",
      "who": "George",
      "conviction": "throwaway"
    },
    {
      "idea": "Premium bidet product for American market (Tushy model)",
      "who": "George",
      "conviction": "throwaway"
    }
  ],
  "predictions": [
    {
      "who": "George",
      "text": "First self-made teenage billionaire will emerge by 2030 via AI and homeschooling boom"
    },
    {
      "who": "George",
      "text": "World will split into nationalism (America First) vs global citizens network states"
    },
    {
      "who": "George",
      "text": "Always-on recording will shift human memory and society similar to written language"
    }
  ]
}
