{
  "approx_date": "2026-02",
  "yt_title": null,
  "business_ideas": [
    {
      "idea": "Smithy Home Couture: luxury custom sewing and alterations for high-end clientele",
      "who": "Guest",
      "conviction": "already building/built"
    },
    {
      "idea": "Sell handmade vests and alterations to neighbors as side business venture",
      "who": "Guest",
      "conviction": "already building/built"
    }
  ],
  "predictions": [
    {
      "who": "Guest",
      "text": "Entrepreneurial parent support beats financial capital for building founder confidence"
    }
  ]
}